.gitignore
.travis.yml
CHANGELOG.rst
LICENSE.txt
MANIFEST.in
README.rst
pytest.ini
setup.py
test.bash
dms_tools2/__init__.py
dms_tools2/_cutils.c
dms_tools2/_metadata.py
dms_tools2/barcodes.py
dms_tools2/compareprefs.py
dms_tools2/diffsel.py
dms_tools2/dssp.py
dms_tools2/fracsurvive.py
dms_tools2/ipython_utils.py
dms_tools2/minimap2.py
dms_tools2/pacbio.py
dms_tools2/parseargs.py
dms_tools2/plot.py
dms_tools2/prefs.py
dms_tools2/protstruct.py
dms_tools2/rplot.py
dms_tools2/rplot_Rcode.R
dms_tools2/seqnumbering.py
dms_tools2/sra.py
dms_tools2/syn_selection.py
dms_tools2/utils.py
dms_tools2.egg-info/PKG-INFO
dms_tools2.egg-info/SOURCES.txt
dms_tools2.egg-info/dependency_links.txt
dms_tools2.egg-info/requires.txt
dms_tools2.egg-info/top_level.txt
docs/.gitignore
docs/.nojekyll
docs/Makefile
docs/README.rst
docs/api.rst
docs/bcsubamp.rst
docs/citations.rst
docs/conf.py
docs/diffsel.rst
docs/dms2_batch_bcsubamp.rst
docs/dms2_batch_diffsel.rst
docs/dms2_batch_fracsurvive.rst
docs/dms2_batch_prefs.rst
docs/dms2_bcsubamp.rst
docs/dms2_diffsel.rst
docs/dms2_fracsurvive.rst
docs/dms2_logoplot.rst
docs/dms2_prefs.rst
docs/examples.rst
docs/fracsurvive.rst
docs/index.rst
docs/installation.rst
docs/prefs.rst
docs/programs.rst
docs/weblinks.txt
docs/_static/BarcodedSubampliconDingens2017.jpg
docs/_static/BarcodedSubampliconDoud2016.jpg
docs/_static/BarcodedSubampliconNotes_Jesse.pdf
docs/_static/BarcodedSubampliconNotes_Mike.pdf
docs/_static/BloomLogo.jpg
docs/_static/DiffSelSnippet.jpg
docs/_static/DiffSelWorkflow.jpg
docs/_static/PrefsSnippet.jpg
docs/_static/PrefsWorkflow.jpg
docs/_static/_facetedGGSeqLogo_test_plot.png
docs/_static/_findSigSel.png
docs/_static/_fit_fourParamLogistics_neutplot.png
docs/_static/_fourParamLogistic_neutplot.png
docs/_static/_plotRarefactionCurves.png
docs/_static/_siteSubsetGGSeqLogo_test_plot.png
docs/_static/custom.ccs
docs/_static/frac_survive_example_plot.pdf
docs/_static/frac_survive_example_plot.png
docs/_static/fracsurvive_example.ipynb
docs/_static/fracsurvive_fig.jpg
examples/.gitignore
examples/README.rst
examples/Dingens2017/README.rst
examples/Dingens2017/analysis_notebook.ipynb
