Metadata-Version: 2.1
Name: dms-tools2
Version: 2.6.11
Summary: Deep mutational scanning (DMS) analysis tools.
Home-page: http://jbloomlab.github.io/dms_tools2
Author: `the Bloom Lab <https://github.com/jbloomlab/dms_tools2/graphs/contributors>`_
Author-email: jbloom@fredhutch.org
License: GPLv3
Download-URL: https://github.com/jbloomlab/dms_tools2/tarball/2.6.11
Platform: Linux and Mac OS X.
Provides-Extra: rplot
License-File: LICENSE.txt
